[{"model": "quiz.exam", "pk": 1, "fields": {"create_timestamp": "2022-02-07T23:21:08.255Z", "update_timestamp": "2022-02-07T23:21:08.255Z", "uuid": "0ab9d093-b341-4a7d-924b-3756d1886a45", "title": "Test by Math", "description": "Тест по математике", "level": 0}}, {"model": "quiz.exam", "pk": 2, "fields": {"create_timestamp": "2022-02-08T00:07:50.009Z", "update_timestamp": "2022-02-08T00:07:50.009Z", "uuid": "04a4c015-3626-4445-b0b6-2e4c89434d72", "title": "Human Systems Test", "description": "Test about humans systems", "level": 1}}, {"model": "quiz.question", "pk": 1, "fields": {"create_timestamp": "2022-02-07T23:21:57.501Z", "update_timestamp": "2022-02-07T23:21:57.501Z", "exam": 1, "order_num": 1, "text": "2 + 2 = ?", "image": ""}}, {"model": "quiz.question", "pk": 2, "fields": {"create_timestamp": "2022-02-07T23:22:55.635Z", "update_timestamp": "2022-02-07T23:22:55.635Z", "exam": 1, "order_num": 2, "text": "45 / 5 = ?", "image": ""}}, {"model": "quiz.question", "pk": 3, "fields": {"create_timestamp": "2022-02-07T23:23:18.408Z", "update_timestamp": "2022-02-07T23:23:18.408Z", "exam": 1, "order_num": 3, "text": "21 * (3 + 5) = ?", "image": ""}}, {"model": "quiz.question", "pk": 4, "fields": {"create_timestamp": "2022-02-08T00:09:12.701Z", "update_timestamp": "2022-02-08T00:09:12.702Z", "exam": 2, "order_num": 1, "text": "Which of the following age groups is not apart of the dependency load?", "image": ""}}, {"model": "quiz.question", "pk": 5, "fields": {"create_timestamp": "2022-02-08T00:09:52.164Z", "update_timestamp": "2022-02-08T00:09:52.164Z", "exam": 2, "order_num": 2, "text": "Which of the following is an example of a Push factor?", "image": ""}}, {"model": "quiz.question", "pk": 6, "fields": {"create_timestamp": "2022-02-08T00:10:53.974Z", "update_timestamp": "2022-02-08T00:10:53.974Z", "exam": 2, "order_num": 3, "text": "Which of the following is an example of a Pull factor?", "image": ""}}, {"model": "quiz.question", "pk": 7, "fields": {"create_timestamp": "2022-02-08T00:12:18.825Z", "update_timestamp": "2022-02-08T00:12:18.825Z", "exam": 2, "order_num": 4, "text": "Which type of immigrant needs to have an ability to make a significant financial contribution to Canada's economy?", "image": ""}}, {"model": "quiz.question", "pk": 8, "fields": {"create_timestamp": "2022-02-08T00:13:23.776Z", "update_timestamp": "2022-02-08T00:13:23.776Z", "exam": 2, "order_num": 5, "text": "Which type of immigrant is reunited with a close family member, who issponsoring them in Canada?", "image": ""}}, {"model": "quiz.choice", "pk": 1, "fields": {"question": 1, "text": "3", "is_correct": false}}, {"model": "quiz.choice", "pk": 2, "fields": {"question": 1, "text": "4", "is_correct": true}}, {"model": "quiz.choice", "pk": 3, "fields": {"question": 1, "text": "5", "is_correct": false}}, {"model": "quiz.choice", "pk": 4, "fields": {"question": 4, "text": "0-4", "is_correct": false}}, {"model": "quiz.choice", "pk": 5, "fields": {"question": 4, "text": "10-14", "is_correct": false}}, {"model": "quiz.choice", "pk": 6, "fields": {"question": 4, "text": "15-19", "is_correct": true}}, {"model": "quiz.choice", "pk": 7, "fields": {"question": 4, "text": "65-69", "is_correct": false}}, {"model": "quiz.choice", "pk": 8, "fields": {"question": 5, "text": "Better job opportunities", "is_correct": false}}, {"model": "quiz.choice", "pk": 9, "fields": {"question": 5, "text": "War", "is_correct": true}}, {"model": "quiz.choice", "pk": 10, "fields": {"question": 5, "text": "Lower Taxes", "is_correct": false}}, {"model": "quiz.choice", "pk": 11, "fields": {"question": 5, "text": "Joining Family", "is_correct": false}}, {"model": "quiz.choice", "pk": 12, "fields": {"question": 6, "text": "Favorable Conditions", "is_correct": true}}, {"model": "quiz.choice", "pk": 13, "fields": {"question": 6, "text": "Religious Persecution", "is_correct": false}}, {"model": "quiz.choice", "pk": 14, "fields": {"question": 6, "text": "Terrorism", "is_correct": false}}, {"model": "quiz.choice", "pk": 15, "fields": {"question": 6, "text": "Natural Disasters", "is_correct": false}}, {"model": "quiz.choice", "pk": 16, "fields": {"question": 7, "text": "Skilled Worker", "is_correct": false}}, {"model": "quiz.choice", "pk": 17, "fields": {"question": 7, "text": "Business Immigrant", "is_correct": true}}, {"model": "quiz.choice", "pk": 18, "fields": {"question": 7, "text": "Family Immigrant", "is_correct": false}}, {"model": "quiz.choice", "pk": 19, "fields": {"question": 7, "text": "Refugee", "is_correct": false}}, {"model": "quiz.choice", "pk": 20, "fields": {"question": 8, "text": "Skilled Worker", "is_correct": false}}, {"model": "quiz.choice", "pk": 21, "fields": {"question": 8, "text": "Business Immigrant", "is_correct": false}}, {"model": "quiz.choice", "pk": 22, "fields": {"question": 8, "text": "Family Immigrant", "is_correct": true}}, {"model": "quiz.choice", "pk": 23, "fields": {"question": 8, "text": "Refugee", "is_correct": false}}]